irrp.py
irrp-1.0.1.dist-info/LICENSE
irrp-1.0.1.dist-info/WHEEL
irrp-1.0.1.dist-info/METADATA
irrp-1.0.1.dist-info/RECORD
