Metadata-Version: 2.1
Name: irrp
Version: 1.0.1
Summary: irrp.py as a python module
Author-email: Fata Nugraha <fatanugraha@outlook.com>
Classifier: License :: OSI Approved :: MIT License
Project-URL: Home, https://github.com/fatanugraha/irrp
